dataclasses_tensor/__init__.py
dataclasses_tensor/adapters.py
dataclasses_tensor/core.py
dataclasses_tensor/layout.py
dataclasses_tensor/utils.py
dataclasses_tensor-0.2.6.dist-info/LICENSE
dataclasses_tensor-0.2.6.dist-info/METADATA
dataclasses_tensor-0.2.6.dist-info/WHEEL
dataclasses_tensor-0.2.6.dist-info/top_level.txt
dataclasses_tensor-0.2.6.dist-info/RECORD
