Metadata-Version: 2.1
Name: dataclasses-tensor
Version: 0.2.6
Summary: Easily serialize dataclasses to and from tensors
Home-page: https://github.com/kachayev/dataclasses-tensor
Author: Oleksii Kachaiev
Author-email: kachayev@gmail.com
License: MIT
Platform: UNKNOWN
Classifier: Intended Audience :: Developers
Classifier: Intended Audience :: Science/Research
Classifier: License :: OSI Approved :: MIT License
Classifier: Programming Language :: Python :: 3
Classifier: Programming Language :: Python :: 3 :: Only
Classifier: Topic :: Software Development :: Libraries
Classifier: Topic :: Software Development :: Libraries :: Python Modules
Requires-Python: >=3.6
Requires-Dist: typing-inspect (>=0.4.0)
Requires-Dist: dataclasses ; python_version == "3.6"
Provides-Extra: tests
Requires-Dist: pytest ; extra == 'tests'
Requires-Dist: ipython ; extra == 'tests'
Requires-Dist: flake8 ; extra == 'tests'
Requires-Dist: numpy (>=1.18.5) ; extra == 'tests'
Requires-Dist: torch (>=1.8.0) ; extra == 'tests'
Requires-Dist: future ; extra == 'tests'
Requires-Dist: hypothesis ; extra == 'tests'
